pygeosimplify/__init__.py
pygeosimplify/cfg/config.py
pygeosimplify/cfg/test_data.py
pygeosimplify/coordinate/definitions.py
pygeosimplify/geo/base.py
pygeosimplify/geo/cells.py
pygeosimplify/io/geo_handler.py
pygeosimplify/simplify/cylinder.py
pygeosimplify/simplify/detector.py
pygeosimplify/simplify/helpers.py
pygeosimplify/simplify/layer.py
pygeosimplify/simplify/post_process.py
pygeosimplify/utils/message_type.py
pygeosimplify/utils/path_resolver.py
pygeosimplify/vis/cylinder.py
pygeosimplify/vis/geo.py
pygeosimplify/vis/scene.py
pygeosimplify-0.0.18.dist-info/LICENSE
pygeosimplify-0.0.18.dist-info/METADATA
pygeosimplify-0.0.18.dist-info/WHEEL
pygeosimplify-0.0.18.dist-info/RECORD
