Metadata-Version: 2.3
Name: pygeosimplify
Version: 0.0.18
Summary: Python package for automatic, cell-based inference of clash-free simplified detector geometry.
Author: Joshua Falco Beirer
Author-email: jbeirer@cern.ch
Requires-Python: >=3.9,<3.13
Classifier: Programming Language :: Python :: 3
Classifier: Programming Language :: Python :: 3.9
Classifier: Programming Language :: Python :: 3.10
Classifier: Programming Language :: Python :: 3.11
Classifier: Programming Language :: Python :: 3.12
Requires-Dist: distinctipy (>=1.3.4,<2.0.0)
Requires-Dist: matplotlib (>=3.9.0,<4.0.0)
Requires-Dist: numpy (>=2.0.2,<3.0.0)
Requires-Dist: pandas (>=2.2.3,<3.0.0)
Requires-Dist: pyg4ometry (>=1.3.5,<2.0.0)
Requires-Dist: scipy (>=1.13.1,<2.0.0)
Requires-Dist: tqdm (>=4.67.1,<5.0.0)
Requires-Dist: uproot (>=5.6.0,<6.0.0)
